setup.py
juicenet/__init__.py
juicenet.egg-info/PKG-INFO
juicenet.egg-info/SOURCES.txt
juicenet.egg-info/dependency_links.txt
juicenet.egg-info/requires.txt
juicenet.egg-info/top_level.txt
juicenet.egg-info/zip-safe