Metadata-Version: 1.0
Name: juicenet
Version: 0.0.2
Summary: Read and control Juicenet/Juicepoint/Juicebox based EVSE devices
Home-page: http://github.com/jesserockz/python-juicenet
Author: Jesse Hills
Author-email: UNKNOWN
License: MIT
Platform: UNKNOWN
